{
  "name": "3D_Developing_brain",
  "url": "https://github.com/samik1986/3D_Developing_brain",
  "description": "Code for Comparison of Cell Detection in 3D Histological Developing Brain",
  "language": "Jupyter Notebook",
  "all_files": {
    "MEDIAR_(model1).ipynb": {
      "filepath": "MEDIAR_(model1).ipynb",
      "size": 19430968,
      "summary": "Defines deep learning model architectures or networks.",
      "is_gpu": false
    },
    "MultiStreamCellSeg_(model_2).ipynb": {
      "filepath": "MultiStreamCellSeg_(model_2).ipynb",
      "size": 5302545,
      "summary": "Defines deep learning model architectures or networks.",
      "is_gpu": false
    },
    "eval1.m": {
      "filepath": "eval1.m",
      "size": 3690,
      "summary": "Contains testing or evaluation scripts.",
      "is_gpu": false
    }
  },
  "repo_insight": "The '3D_Developing_brain' repository offers a comprehensive computational framework for comparing different cell detection methodologies within complex 3D histological images of developing brain tissue, serving a vital role in the domain of bioimage informatics and developmental neuroscience. Its holistic capability is to benchmark and assess the efficacy of various algorithms for accurately identifying and localizing cells in volumetric microscopy data, which is fundamental for understanding neurogenesis, cell migration patterns, and disease progression in brain development. The intended usage involves users first engaging with the two provided Jupyter notebooks, MEDIAR_(model1).ipynb and MultiStreamCellSeg_(model_2).ipynb, which serve as executable pipelines to apply and generate cell detection results using two distinct computational models on their 3D image datasets. Following the generation of these detections, the eval1.m MATLAB script is designed to load the model outputs alongside ground truth data to perform a rigorous, quantitative evaluation and comparison of the models' performance, likely calculating metrics such as precision, recall, and F1-score. Architecturally, the project highlights the implementation of two sophisticated cell detection algorithms\u2014one named MEDIAR and the other, MultiStreamCellSeg, which strongly suggests a multi-stream neural network designed for robust segmentation\u2014with their development and application orchestrated within the interactive and iterative Python-based Jupyter environment. The separation of model execution in Python notebooks and the dedicated evaluation in a MATLAB script underscores a common research practice where advanced deep learning methods are built in Python while robust, often standardized, quantitative analysis and reporting are performed using MATLAB's scientific computing capabilities."
}